boilergen/__init__.py
boilergen/__main__.py
boilergen/builder/__init__.py
boilergen/builder/generation_logic.py
boilergen/builder/hooks.py
boilergen/builder/output_selection.py
boilergen/builder/project_setup.py
boilergen/builder/parser/__init__.py
boilergen/builder/parser/configs.py
boilergen/builder/parser/injections.py
boilergen/builder/parser/tags.py
boilergen/cli/__init__.py
boilergen/cli/commands.py
boilergen/cli/run_config.py
boilergen/core/__init__.py
boilergen/core/display.py
boilergen/core/navigator.py
boilergen/core/template.py
boilergen/core/template_finder.py
boilergen/templates/gh-Workflows/Realease Version to Github/template.yaml
boilergen/templates/gh-Workflows/Realease Version to Github/template/.github/workflows/flutter-release.yml
boilergen-1.3.2.post2.dist-info/METADATA
boilergen-1.3.2.post2.dist-info/WHEEL
boilergen-1.3.2.post2.dist-info/entry_points.txt
boilergen-1.3.2.post2.dist-info/RECORD
